Metadata-Version: 2.1
Name: my-new-release-project-aba1
Version: 0.1.1
Summary: good job
Author: kirill
Author-email: KARum2004@yandex.ru
